main.py
mseep_documentation-0.1.10.dist-info/licenses/LICENSE
mseep_documentation-0.1.10.dist-info/METADATA
mseep_documentation-0.1.10.dist-info/WHEEL
mseep_documentation-0.1.10.dist-info/entry_points.txt
mseep_documentation-0.1.10.dist-info/top_level.txt
mseep_documentation-0.1.10.dist-info/RECORD
