Metadata-Version: 2.4
Name: mseep-documentation
Version: 0.1.10
Summary: Add your description here
Author-email: mseep <support@skydeck.ai>
Requires-Python: >=3.11
License-File: LICENSE
Requires-Dist: beautifulsoup4>=4.13.3
Requires-Dist: httpx>=0.28.1
Requires-Dist: mcp[cli]>=1.3.0
Requires-Dist: langchain>=0.1.0
Requires-Dist: langchain-community>=0.1.0
Requires-Dist: langchain-core>=0.1.0
Requires-Dist: chromadb>=0.4.22
Dynamic: license-file
